aliros/__cli__.py
aliros/__init__.py
aliros/alicloud.py
aliros/request.py
aliros/template.py
aliros/types.py
aliros/commands/__init__.py
aliros/commands/abandon_stack.py
aliros/commands/create_stack.py
aliros/commands/delete_stack.py
aliros/commands/describe_resource_type.py
aliros/commands/describe_resource_type_template.py
aliros/commands/describe_stack.py
aliros/commands/describe_stack_resource.py
aliros/commands/describe_stack_template.py
aliros/commands/list_regions.py
aliros/commands/list_resource_types.py
aliros/commands/list_stack_events.py
aliros/commands/list_stack_resources.py
aliros/commands/list_stacks.py
aliros/commands/preview_stack.py
aliros/commands/update_stack.py
aliros/commands/validate_template.py
aliros-1.5.1.dist-info/METADATA
aliros-1.5.1.dist-info/WHEEL
aliros-1.5.1.dist-info/entry_points.txt
aliros-1.5.1.dist-info/licenses/LICENSE
aliros-1.5.1.dist-info/RECORD
