Metadata-Version: 2.4
Name: aliros
Version: 1.5.1
Summary: A command-line tool to organize resources by Resource Orchestration Service for Alibaba Cloud.
Project-URL: homepage, https://github.com/garrett-he/aliros
Project-URL: repository, https://github.com/garrett-he/aliros.git
Author-email: Garrett HE <garrett.he@outlook.com>
License: BSD-3-Clause
License-File: LICENSE
Keywords: alicloud,devops,ros
Requires-Python: <3.13,>=3.10
Requires-Dist: aliyun-python-sdk-core>=2.16.0
Requires-Dist: aliyun-python-sdk-ros>=3.6.0
Requires-Dist: click>=8.1.7
